vtime/__init__.py
vtime/vtime.py
vtime-2.0.0.dist-info/LICENSE.txt
vtime-2.0.0.dist-info/WHEEL
vtime-2.0.0.dist-info/METADATA
vtime-2.0.0.dist-info/RECORD
