Metadata-Version: 2.1
Name: vtime
Version: 2.0.0
Summary: Time related functions
Home-page: https://github.com/villoro/vtime
License: MIT
Author: Arnau Villoro
Author-email: arnau@villoro.com
Maintainer: Arnau Villoro
Maintainer-email: arnau@villoro.com
Requires-Python: >=3.6.1,<4.0.0
Classifier: Intended Audience :: Developers
Classifier: Intended Audience :: Education
Classifier: Intended Audience :: Manufacturing
Classifier: Intended Audience :: Science/Research
Classifier: License :: OSI Approved :: MIT License
Classifier: Programming Language :: Python
Classifier: Programming Language :: Python :: 3
Classifier: Programming Language :: Python :: 3.6
Classifier: Programming Language :: Python :: 3.7
Classifier: Programming Language :: Python :: 3.8
Project-URL: Repository, https://github.com/villoro/vtime
